odoo/addons/l10n_ro_stock_account_date/README.rst
odoo/addons/l10n_ro_stock_account_date/__init__.py
odoo/addons/l10n_ro_stock_account_date/__manifest__.py
odoo/addons/l10n_ro_stock_account_date/i18n/l10n_ro_stock_account_date.pot
odoo/addons/l10n_ro_stock_account_date/i18n/ro.po
odoo/addons/l10n_ro_stock_account_date/models/__init__.py
odoo/addons/l10n_ro_stock_account_date/models/stock_move.py
odoo/addons/l10n_ro_stock_account_date/models/stock_picking.py
odoo/addons/l10n_ro_stock_account_date/models/stock_quant.py
odoo/addons/l10n_ro_stock_account_date/readme/CONTRIBUTORS.md
odoo/addons/l10n_ro_stock_account_date/readme/DESCRIPTION.md
odoo/addons/l10n_ro_stock_account_date/readme/INSTALL.md
odoo/addons/l10n_ro_stock_account_date/static/description/icon.png
odoo/addons/l10n_ro_stock_account_date/static/description/index.html
odoo/addons/l10n_ro_stock_account_date/tests/__init__.py
odoo/addons/l10n_ro_stock_account_date/tests/test_stock_accounting_date.py
odoo/addons/l10n_ro_stock_account_date/views/stock_picking_views.xml
odoo_addon_l10n_ro_stock_account_date-19.0.0.1.0.1.dist-info/METADATA
odoo_addon_l10n_ro_stock_account_date-19.0.0.1.0.1.dist-info/WHEEL
odoo_addon_l10n_ro_stock_account_date-19.0.0.1.0.1.dist-info/top_level.txt
odoo_addon_l10n_ro_stock_account_date-19.0.0.1.0.1.dist-info/RECORD
